pycrp/__init__.py
pycrp/cli.py
pycrp/exceptions.py
pycrp/main.py
pycrp-1.0.1.dist-info/LICENSE
pycrp-1.0.1.dist-info/METADATA
pycrp-1.0.1.dist-info/WHEEL
pycrp-1.0.1.dist-info/entry_points.txt
pycrp-1.0.1.dist-info/top_level.txt
pycrp-1.0.1.dist-info/RECORD
