Metadata-Version: 2.1
Name: pycrp
Version: 1.0.1
Summary: A Python package for securely encrypting and decrypting files with advanced algorithms.
Author: Hossein gasemzadeh
Author-email: hossein.gasemzadeh03@gmail.com
License-File: LICENSE
Requires-Dist: cryptography ==42.0.8
Requires-Dist: termcolor ==2.4.0
